sketchbook/__init__.py
sketchbook/_version.py
sketchbook/context.py
sketchbook/escaping.py
sketchbook/exceptions.py
sketchbook/finders.py
sketchbook/parser.py
sketchbook/printer.py
sketchbook/py.typed
sketchbook/runtime.py
sketchbook/sketch.py
sketchbook/statements.py
sketchbook/testutils.py
sketchbook/utils.py
sketchbook-0.3.0.dist-info/LICENSE
sketchbook-0.3.0.dist-info/WHEEL
sketchbook-0.3.0.dist-info/METADATA
sketchbook-0.3.0.dist-info/RECORD
