Metadata-Version: 2.1
Name: sketchbook
Version: 0.3.0
Summary: A template engine built for asyncio with async/await syntax support.
Home-page: https://github.com/futursolo/sketchbook
License: Apache-2.0
Author: Kaede Hoshikawa
Author-email: futursolo@icloud.com
Requires-Python: >=3.8.0,<4.0.0
Classifier: License :: OSI Approved :: Apache Software License
Classifier: Operating System :: MacOS
Classifier: Operating System :: MacOS :: MacOS X
Classifier: Operating System :: Microsoft
Classifier: Operating System :: Microsoft :: Windows
Classifier: Operating System :: POSIX
Classifier: Operating System :: POSIX :: Linux
Classifier: Operating System :: Unix
Classifier: Programming Language :: Python
Classifier: Programming Language :: Python :: 3
Classifier: Programming Language :: Python :: 3 :: Only
Classifier: Programming Language :: Python :: 3.8
Classifier: Programming Language :: Python :: 3.9
Classifier: Programming Language :: Python :: Implementation :: CPython
Provides-Extra: aiofiles
Provides-Extra: curio
Provides-Extra: docs
Provides-Extra: full
Requires-Dist: aiofiles (>=0.6,<0.8); extra == "aiofiles" or extra == "full" or extra == "docs"
Requires-Dist: curio (>=1.5,<2.0); extra == "curio" or extra == "full" or extra == "docs"
Requires-Dist: importlib-metadata (>=4.0.1,<5.0.0); python_version <= "3.7"
Requires-Dist: sphinx (>=4.1,<5.0); extra == "docs"
Requires-Dist: sphinx-rtd-dark-mode (>=1.2.4,<2.0.0); extra == "docs"
Requires-Dist: sphinx_rtd_theme (>=1.0,<2.0); extra == "docs"
Requires-Dist: sphinxcontrib-asyncio (>=0.3.0,<0.4.0); extra == "docs"
Project-URL: Repository, https://github.com/futursolo/sketchbook
